flarecast/__init__.py
flarecast/utils/__init__.py
flarecast/utils/cadence.py
flarecast/utils/flarecast_config.py
flarecast/utils/property_service_client.py
flarecast/utils/rest_exception.py
flarecast_utils-1.4.1.174.dist-info/DESCRIPTION.rst
flarecast_utils-1.4.1.174.dist-info/METADATA
flarecast_utils-1.4.1.174.dist-info/RECORD
flarecast_utils-1.4.1.174.dist-info/WHEEL
flarecast_utils-1.4.1.174.dist-info/metadata.json
flarecast_utils-1.4.1.174.dist-info/top_level.txt
