Metadata-Version: 2.0
Name: flarecast-utils
Version: 1.4.1.174
Summary: Flarecast utils provides tools to interact with the flarecast infrastructure.
Home-page: https://dev.flarecast.eu/stash/projects/INFRA/repos/utils/
Author: Florian Bruggisser
Author-email: florian.bruggisser@students.fhnw.ch
License: UNKNOWN
Download-URL: https://dev.flarecast.eu/stash/scm/infra/utils.git
Keywords: flarecast,utils,esa,solar,weather,prediction
Platform: UNKNOWN
Classifier: Programming Language :: Python
Classifier: Programming Language :: Python :: 2.7
Classifier: Development Status :: 4 - Beta
Classifier: Intended Audience :: Developers
Classifier: Operating System :: OS Independent
Requires-Dist: requests
